influxdb_datalogger/__init__.py
influxdb_datalogger/datalogger.py
influxdb_datalogger/datalogger_map.py
influxdb_datalogger/field.py
influxdb_datalogger/measurement.py
influxdb_datalogger/tag.py
influxdb_datalogger/utils.py
influxdb_datalogger-2.4.2.dist-info/LICENSE
influxdb_datalogger-2.4.2.dist-info/METADATA
influxdb_datalogger-2.4.2.dist-info/WHEEL
influxdb_datalogger-2.4.2.dist-info/top_level.txt
influxdb_datalogger-2.4.2.dist-info/RECORD
