Metadata-Version: 2.1
Name: influxdb-datalogger
Version: 2.4.2
Summary: A package that assists with logging data from a test and writing it to a database like InfluxDB.
Home-page: https://bitbucket.org/dataductus/influxdb-datalogger
Author: Chloe Holst
Author-email: chloe.holst@dataductus.se
License: Apache 2.0
Classifier: License :: OSI Approved :: Apache Software License
Classifier: Programming Language :: Python :: 3
Classifier: Programming Language :: Python :: 3.8
License-File: LICENSE
